MANIFEST.in
README.rst
setup.py
tallyclient/__init__.py
tallyclient.egg-info/PKG-INFO
tallyclient.egg-info/SOURCES.txt
tallyclient.egg-info/dependency_links.txt
tallyclient.egg-info/not-zip-safe
tallyclient.egg-info/top_level.txt