Metadata-Version: 1.0
Name: tallyclient
Version: 0.1
Summary: Python client for go-tally server
Home-page: https://github.com/phouse512/tally-client
Author: phouse512
Author-email: phouse512@gmail.com
License: MIT
Platform: UNKNOWN
